current_temp_api/__init__.py
current_temp_api/api.py
current_temp_api/base.py
current_temp_api-0.0.1.19416830.dist-info/LICENSE
current_temp_api-0.0.1.19416830.dist-info/METADATA
current_temp_api-0.0.1.19416830.dist-info/WHEEL
current_temp_api-0.0.1.19416830.dist-info/top_level.txt
current_temp_api-0.0.1.19416830.dist-info/RECORD
